TensorflowJuanjiShenjingwangluoShiyongZhinanChuyiFix1/README.md
TensorflowJuanjiShenjingwangluoShiyongZhinanChuyiFix1/__init__.py
TensorflowJuanjiShenjingwangluoShiyongZhinanChuyiFix1/__main__.py
TensorflowJuanjiShenjingwangluoShiyongZhinanChuyiFix1/file.epub
TensorflowJuanjiShenjingwangluoShiyongZhinanChuyiFix1/index.html
TensorflowJuanjiShenjingwangluoShiyongZhinanChuyiFix1/css/__init__.py
TensorflowJuanjiShenjingwangluoShiyongZhinanChuyiFix1/css/annotations.css
TensorflowJuanjiShenjingwangluoShiyongZhinanChuyiFix1/css/main.css
TensorflowJuanjiShenjingwangluoShiyongZhinanChuyiFix1/css/normalize.css
TensorflowJuanjiShenjingwangluoShiyongZhinanChuyiFix1/css/popup.css
TensorflowJuanjiShenjingwangluoShiyongZhinanChuyiFix1/font/__init__.py
TensorflowJuanjiShenjingwangluoShiyongZhinanChuyiFix1/font/fontello.eot
TensorflowJuanjiShenjingwangluoShiyongZhinanChuyiFix1/font/fontello.svg
TensorflowJuanjiShenjingwangluoShiyongZhinanChuyiFix1/font/fontello.ttf
TensorflowJuanjiShenjingwangluoShiyongZhinanChuyiFix1/font/fontello.woff
TensorflowJuanjiShenjingwangluoShiyongZhinanChuyiFix1/img/__init__.py
TensorflowJuanjiShenjingwangluoShiyongZhinanChuyiFix1/img/annotator-glyph-sprite.png
TensorflowJuanjiShenjingwangluoShiyongZhinanChuyiFix1/img/annotator-icon-sprite.png
TensorflowJuanjiShenjingwangluoShiyongZhinanChuyiFix1/img/apple-touch-icon.png
TensorflowJuanjiShenjingwangluoShiyongZhinanChuyiFix1/img/cancelfullscreen.png
TensorflowJuanjiShenjingwangluoShiyongZhinanChuyiFix1/img/close.png
TensorflowJuanjiShenjingwangluoShiyongZhinanChuyiFix1/img/fullscreen.png
TensorflowJuanjiShenjingwangluoShiyongZhinanChuyiFix1/img/loader.gif
TensorflowJuanjiShenjingwangluoShiyongZhinanChuyiFix1/img/menu-icon.png
TensorflowJuanjiShenjingwangluoShiyongZhinanChuyiFix1/img/save.png
TensorflowJuanjiShenjingwangluoShiyongZhinanChuyiFix1/img/saved.png
TensorflowJuanjiShenjingwangluoShiyongZhinanChuyiFix1/img/settings-s.png
TensorflowJuanjiShenjingwangluoShiyongZhinanChuyiFix1/img/settings.png
tensorflow_juanji_shenjingwangluo_shiyong_zhinan_chuyi_fix1-2025.3.24.1.dist-info/METADATA
tensorflow_juanji_shenjingwangluo_shiyong_zhinan_chuyi_fix1-2025.3.24.1.dist-info/WHEEL
tensorflow_juanji_shenjingwangluo_shiyong_zhinan_chuyi_fix1-2025.3.24.1.dist-info/entry_points.txt
tensorflow_juanji_shenjingwangluo_shiyong_zhinan_chuyi_fix1-2025.3.24.1.dist-info/top_level.txt
tensorflow_juanji_shenjingwangluo_shiyong_zhinan_chuyi_fix1-2025.3.24.1.dist-info/RECORD
